AUTHORS.rst
CONTRIBUTING.rst
HISTORY.rst
LICENSE
MANIFEST.in
README.rst
setup.cfg
setup.py
docs/Makefile
docs/authors.rst
docs/conf.py
docs/contributing.rst
docs/history.rst
docs/index.rst
docs/installation.rst
docs/make.bat
docs/readme.rst
docs/usage.rst
outspect/__init__.py
outspect/outspect.py
outspect.egg-info/PKG-INFO
outspect.egg-info/SOURCES.txt
outspect.egg-info/dependency_links.txt
outspect.egg-info/not-zip-safe
outspect.egg-info/top_level.txt
tests/__init__.py
tests/test_outspect.py